db/__init__.py
db/api.py
db/tables.py
tikki-0.9.0.dist-info/METADATA
tikki-0.9.0.dist-info/RECORD
tikki-0.9.0.dist-info/WHEEL
tikki-0.9.0.dist-info/top_level.txt
