Metadata-Version: 2.1
Name: tikki
Version: 0.9.0
Summary: Tikki Field Aptitude Performance Data Collection Platform
Home-page: https://github.com/tikki-fi/tikki
Author: RESUL Ry
Author-email: info@resul.fi
Maintainer: Ville Brofeldt
Maintainer-email: ville.brofeldt@streamroller.io
License: MIT
Platform: UNKNOWN
Classifier: Programming Language :: Python :: 3.6
Classifier: Programming Language :: Python :: 3.7
Classifier: Intended Audience :: Developers
Classifier: License :: OSI Approved :: MIT License
Classifier: Natural Language :: English
Requires-Dist: alembic
Requires-Dist: flask
Requires-Dist: flask-cors
Requires-Dist: flask-jwt-simple
Requires-Dist: python-dateutil
Requires-Dist: sqlalchemy
Requires-Dist: sqlalchemy-utils
Requires-Dist: werkzeug
